README.md
setup.py
dj_saferunner.egg-info/PKG-INFO
dj_saferunner.egg-info/SOURCES.txt
dj_saferunner.egg-info/dependency_links.txt
dj_saferunner.egg-info/top_level.txt
saferunner/__init__.py
saferunner/assertions.py
saferunner/process_runner.py
saferunner/tasks.py
saferunner/test.py