Metadata-Version: 2.1
Name: dj-saferunner
Version: 0.0.2
Summary: UNKNOWN
Home-page: https://gitlab.com/schoolorchestration/libs/dj-saferunner
Author: Christo Crampton
Author-email: info@38.co.za
License: UNKNOWN
Platform: UNKNOWN
Classifier: Programming Language :: Python :: 3
Classifier: Operating System :: OS Independent
